aerleon/__init__.py
aerleon/__main__.py
aerleon/_vendor/ply/LICENSE
aerleon/_vendor/ply/__init__.py
aerleon/_vendor/ply/cpp.py
aerleon/_vendor/ply/ctokens.py
aerleon/_vendor/ply/lex.py
aerleon/_vendor/ply/yacc.py
aerleon/_vendor/ply/ygen.py
aerleon/aclcheck_cmdline.py
aerleon/aclgen.py
aerleon/api.py
aerleon/lib/COPYING
aerleon/lib/__init__.py
aerleon/lib/aclcheck.py
aerleon/lib/aclgenerator.py
aerleon/lib/addressbook.py
aerleon/lib/arista.py
aerleon/lib/arista_tp.py
aerleon/lib/aruba.py
aerleon/lib/brocade.py
aerleon/lib/cisco.py
aerleon/lib/ciscoasa.py
aerleon/lib/cisconx.py
aerleon/lib/ciscoxr.py
aerleon/lib/cloudarmor.py
aerleon/lib/demo.py
aerleon/lib/fortigate.py
aerleon/lib/fqdn.py
aerleon/lib/gce.py
aerleon/lib/gcp.py
aerleon/lib/gcp_hf.py
aerleon/lib/ipset.py
aerleon/lib/iptables.py
aerleon/lib/juniper.py
aerleon/lib/juniperevo.py
aerleon/lib/junipermsmpc.py
aerleon/lib/junipersrx.py
aerleon/lib/k8s.py
aerleon/lib/nacaddr.py
aerleon/lib/naming.py
aerleon/lib/nftables.py
aerleon/lib/nokiasrl.py
aerleon/lib/nsxt.py
aerleon/lib/nsxv.py
aerleon/lib/nvueapi.py
aerleon/lib/openconfig.py
aerleon/lib/packetfilter.py
aerleon/lib/paloaltofw.py
aerleon/lib/pcap.py
aerleon/lib/plugin.py
aerleon/lib/plugin_supervisor.py
aerleon/lib/policy.py
aerleon/lib/policy_builder.py
aerleon/lib/policy_simple.py
aerleon/lib/policyreader.py
aerleon/lib/port.py
aerleon/lib/proxmox.py
aerleon/lib/recognizers.py
aerleon/lib/sonic.py
aerleon/lib/speedway.py
aerleon/lib/srxlo.py
aerleon/lib/summarizer.py
aerleon/lib/windows.py
aerleon/lib/windows_advfirewall.py
aerleon/lib/windows_ipsec.py
aerleon/lib/yaml.py
aerleon/lib/yaml_loader.py
aerleon/py.typed
aerleon/utils/__init__.py
aerleon/utils/config.py
aerleon/utils/iputils.py
aerleon/utils/options.py
tools/__init__.py
tools/cgrep.py
tools/iputilstools.py
aerleon-1.14.1.dist-info/METADATA
aerleon-1.14.1.dist-info/WHEEL
aerleon-1.14.1.dist-info/entry_points.txt
aerleon-1.14.1.dist-info/licenses/AUTHORS
aerleon-1.14.1.dist-info/licenses/LICENSE
aerleon-1.14.1.dist-info/RECORD
