Metadata-Version: 2.4
Name: aerleon
Version: 1.14.1
Summary: A firewall generation tool
License-Expression: Apache-2.0
License-File: AUTHORS
License-File: LICENSE
Keywords: firewall,networking,security
Author: Jason Benterou
Author-email: jason.benterou@gmail.com
Requires-Python: >=3.10,<4.0
Classifier: Development Status :: 5 - Production/Stable
Classifier: Operating System :: OS Independent
Classifier: Programming Language :: Python :: 3
Classifier: Programming Language :: Python :: 3.10
Classifier: Programming Language :: Python :: 3.11
Classifier: Programming Language :: Python :: 3.12
Classifier: Programming Language :: Python :: 3.13
Classifier: Programming Language :: Python :: 3.14
Classifier: Topic :: Security
Classifier: Topic :: System :: Networking :: Firewalls
Requires-Dist: PyYAML (>=6.0.3,<7.0.0)
Requires-Dist: absl-py (>=2.3.1,<3.0.0)
Requires-Dist: importlib-metadata (>=4.2,<5.0) ; python_version <= "3.10"
Requires-Dist: typing_extensions (>=4.15.0,<5.0.0)
Project-URL: Homepage, https://github.com/aerleon/aerleon
Project-URL: Repository, https://github.com/aerleon/aerleon
